wangle/__init__.py
wangle/structure.py
wangle/french/__init__.py
wangle/french/adjective.py
wangle/french/conjugation.py
wangle/french/conjugator.py
wangle/french/declension.py
wangle/french/decliner.py
wangle/french/helper.py
wangle/french/inflection.py
wangle/french/pronoun.py
wangle/french/structure.py
wangle/french/test_adjective.py
wangle/french/test_conjugation.py
wangle/french/test_conjugator.py
wangle/french/test_declension.py
wangle/french/test_decliner.py
wangle/french/test_inflection.py
wangle/french/test_pronoun.py
wangle/french/test_structure.py
wangle/french/test_verb.py
wangle/french/verb.py
wangle/german/__init__.py
wangle/german/conjugator.py
wangle/german/test_conjugator.py
wangle-0.1.2.dist-info/LICENSE
wangle-0.1.2.dist-info/METADATA
wangle-0.1.2.dist-info/WHEEL
wangle-0.1.2.dist-info/top_level.txt
wangle-0.1.2.dist-info/RECORD
