Metadata-Version: 2.1
Name: wangle
Version: 0.1.2
Summary: A python library for natural language manipulation.
Home-page: https://github.com/benjaminharpin/wangle
Author: Ben Harpin
Author-email: benjaminharpin@gmail.com
License: UNKNOWN
Platform: UNKNOWN
Classifier: Programming Language :: Python :: 3
Classifier: License :: OSI Approved :: MIT License
Classifier: Operating System :: OS Independent
